maive/__init__.py
maive/maive.py
MAIVE-0.0.3.2.dist-info/LICENSE
MAIVE-0.0.3.2.dist-info/METADATA
MAIVE-0.0.3.2.dist-info/WHEEL
MAIVE-0.0.3.2.dist-info/top_level.txt
MAIVE-0.0.3.2.dist-info/RECORD
