Metadata-Version: 2.1
Name: MAIVE
Version: 0.0.3.2
Summary: Mathematics and Ariticial Intelligence and Visualization Extended
Author: Piyush Pant
Author-email: piyushpant15@gmail.com
Keywords: MAIVE,Artificial Intelligence,Machine Learning,Maths
Classifier: Programming Language :: Python :: 3
Classifier: License :: OSI Approved :: MIT License
Classifier: Operating System :: OS Independent
License-File: LICENSE
Requires-Dist: numpy
Requires-Dist: matplotlib
Requires-Dist: pandas
Requires-Dist: statsmodels
Requires-Dist: seaborn
Requires-Dist: scikit-learn
Requires-Dist: tensorflow
